MANIFEST.in
README.rst
setup.py
docs/HISTORY.txt
docs/LICENSE.GPL
docs/LICENSE.txt
ftw/__init__.py
ftw.dashboard.portlets.favourites.egg-info/PKG-INFO
ftw.dashboard.portlets.favourites.egg-info/SOURCES.txt
ftw.dashboard.portlets.favourites.egg-info/dependency_links.txt
ftw.dashboard.portlets.favourites.egg-info/entry_points.txt
ftw.dashboard.portlets.favourites.egg-info/namespace_packages.txt
ftw.dashboard.portlets.favourites.egg-info/not-zip-safe
ftw.dashboard.portlets.favourites.egg-info/requires.txt
ftw.dashboard.portlets.favourites.egg-info/top_level.txt
ftw/dashboard/__init__.py
ftw/dashboard/portlets/__init__.py
ftw/dashboard/portlets/favourites/__init__.py
ftw/dashboard/portlets/favourites/adapter.py
ftw/dashboard/portlets/favourites/configure.zcml
ftw/dashboard/portlets/favourites/interfaces.py
ftw/dashboard/portlets/favourites/testing.py
ftw/dashboard/portlets/favourites/browser/__init__.py
ftw/dashboard/portlets/favourites/browser/configure.zcml
ftw/dashboard/portlets/favourites/browser/favourite.py
ftw/dashboard/portlets/favourites/browser/favourites.py
ftw/dashboard/portlets/favourites/browser/resources/favourite.js
ftw/dashboard/portlets/favourites/browser/resources/icon_add_favorite.gif
ftw/dashboard/portlets/favourites/browser/resources/icon_remove_favourite.gif
ftw/dashboard/portlets/favourites/browser/resources/icon_rename_favourite.gif
ftw/dashboard/portlets/favourites/browser/resources/icon_submit_favourite.gif
ftw/dashboard/portlets/favourites/browser/resources/portlet.css
ftw/dashboard/portlets/favourites/locales/__init__.py
ftw/dashboard/portlets/favourites/locales/ftw.dashboard.portlets.favourites.pot
ftw/dashboard/portlets/favourites/locales/plone.pot
ftw/dashboard/portlets/favourites/locales/de/LC_MESSAGES/ftw.dashboard.portlets.favourites.po
ftw/dashboard/portlets/favourites/locales/de/LC_MESSAGES/plone.po
ftw/dashboard/portlets/favourites/locales/fr/LC_MESSAGES/ftw.dashboard.portlets.favourites.po
ftw/dashboard/portlets/favourites/locales/fr/LC_MESSAGES/plone.po
ftw/dashboard/portlets/favourites/locales/pt_BR/LC_MESSAGES/ftw.dashboard.portlets.favourites.po
ftw/dashboard/portlets/favourites/portlets/__init__.py
ftw/dashboard/portlets/favourites/portlets/configure.zcml
ftw/dashboard/portlets/favourites/portlets/favourites.py
ftw/dashboard/portlets/favourites/portlets/templates/favourites.pt
ftw/dashboard/portlets/favourites/profiles/annotationstorage/actions.xml
