Metadata-Version: 1.1
Name: ftw.dashboard.portlets.favourites
Version: 3.5.0
Summary: A favourite Portlet
Home-page: https://github.com/4teamwork/ftw.dashboard.portlets.favourites
Author: 4teamwork AG
Author-email: mailto:info@4teamwork.ch
License: GPL2
Keywords: ftw dashboard portlet favourites favorites
Platform: UNKNOWN
Classifier: Framework :: Plone
Classifier: Framework :: Plone :: 4.1
Classifier: Framework :: Plone :: 4.2
Classifier: Intended Audience :: Developers
Classifier: License :: OSI Approved :: GNU General Public License (GPL)
Classifier: Programming Language :: Python
Classifier: Programming Language :: Python :: 2.6
Classifier: Topic :: Software Development :: Libraries :: Python Modules
